Counter_0_to_15/Source_Codes/Counter0to15.v
module Counter0to15 (Count,Clk);

input Clk;
output [3:0] Count;

reg [3:0] Count;

initial begin

Count <= 0;
 
end

always @ (posedge Clk) begin

	Count <= Count + 1;

end 

endmodule

Counter_0_to_15/Source_Codes/Counter0to15TestBench.v
module Counter0to15TestBench;

reg Clk;
wire [3:0] Count;
logic [13:0] Testvectors[0:99];

Counter0to15 Counter (Count,Clk);
initial begin
	$dumpfile("The_output.vcd");
	$dumpvars(0,Count);
	$dumpvars(0,Clk);
	$readmemb("memory_binary.txt", Testvectors);
end

initial begin 
Clk=0;
repeat(40) #5 Clk=~Clk;
$finish;

end

endmodule

Counter_0_to_15/Source_Codes/The_output.vcd
$date
	Fri Jun 16 05:09:43 2023
$end
$version
	Icarus Verilog
$end
$timescale
	1s
$end
$scope module Counter0to15TestBench $end
$var wire 4 ! Count [3:0] $end
$upscope $end
$scope module Counter0to15TestBench $end
$var reg 1 " Clk $end
$upscope $end
$enddefinitions $end
#0
$dumpvars
0"
b0 !
$end
#5
b1 !
1"
#10
0"
#15
b10 !
1"
#20
0"
#25
b11 !
1"
#30
0"
#35
b100 !
1"
#40
0"
#45
b101 !
1"
#50
0"
#55
b110 !
1"
#60
0"
#65
b111 !
1"
#70
0"
#75
b1000 !
1"
#80
0"
#85
b1001 !
1"
#90
0"
#95
b1010 !
1"
#100
0"
#105
b1011 !
1"
#110
0"
#115
b1100 !
1"
#120
0"
#125
b1101 !
1"
#130
0"
#135
b1110 !
1"
#140
0"
#145
b1111 !
1"
#150
0"
#155
b0 !
1"
#160
0"
#165
b1 !
1"
#170
0"
#175
b10 !
1"
#180
0"
#185
b11 !
1"
#190
0"
#195
b100 !
1"
