Mux/Source_Codes/mux.v
module mux(a,b,c,d, sel, out);

    input a,b,c,d;
    input[1:0] sel;
    output reg out;

    always @(a,b,c,d,sel)
        case(sel)
            0: out <= a;
            1: out <= b;
            2: out <= c;
            default: out <= d;
        endcase

endmodule

Mux/Source_Codes/mux_tb.v
module alu_tb;

    reg a,b,c,d;
    reg [1:0] sel;
    wire out;
    reg Fault_Indicator;


    mux DUT(a,b,c,d, sel, out);

    initial begin
        $dumpfile("The_output.vcd");
        $dumpvars(0,a);
        $dumpvars(0,b);
        $dumpvars(0,c);
        $dumpvars(0,d);
        $dumpvars(0,sel);
        $dumpvars(0,out);
        $dumpvars(0,Fault_Indicator);

        Fault_Indicator = 0;
    end

    initial begin
        a = 0;
        b = 1;
        c = 0;
        d = 1;
        sel = 00;

        #5;
        if(out != 0) begin
            $display("Test FAILED For (%b %b %b %b and sel=%b) (Expected Result: out->0) (But ALU Result is: s->%b)!!  ", a, b, c, d, sel, out);
            Fault_Indicator = 1;
        end
        else begin
            $display("Test Passed For (%b %b %b %b and sel=%b) (Expected Result: out->0) (And ALU Result is: c->%d) ", a, b, c, d, sel, out);
            Fault_Indicator = 0;
        end

        a = 0;
        b = 1;
        c = 0;
        d = 1;
        sel = 01;
        #5;

        if(out != 1) begin
            $display("Test FAILED For (%b %b %b %b and sel=%b) (Expected Result: out->1) (But ALU Result is: s->%b)!!  ", a, b, c, d, sel, out);
            Fault_Indicator = 1;
        end
        else begin
            $display("Test Passed For (%b %b %b %b and sel=%b) (Expected Result: out->1) (And ALU Result is: c->%d) ", a, b, c, d, sel, out);
            Fault_Indicator = 0;
        end

        a = 0;
        b = 1;
        c = 0;
        d = 1;
        sel = 10;
        #5;
        if(out != 0) begin
            $display("Test FAILED For (%b %b %b %b and sel=%b) (Expected Result: out->0) (But ALU Result is: s->%b)!!  ", a, b, c, d, sel, out);
            Fault_Indicator = 1;
        end
        else begin
            $display("Test Passed For (%b %b %b %b and sel=%b) (Expected Result: out->0) (And ALU Result is: c->%d) ", a, b, c, d, sel, out);
            Fault_Indicator = 0;
        end
        a = 0;
        b = 1;
        c = 0;
        d = 1;
        sel = 11;

        #5;
        if(out != 1) begin
            $display("Test FAILED For (%b %b %b %b and sel=%b) (Expected Result: out->1) (But ALU Result is: s->%b)!!  ", a, b, c, d, sel, out);
            Fault_Indicator = 1;
        end
        else begin
            $display("Test Passed For (%b %b %b %b and sel=%b) (Expected Result: out->1) (And ALU Result is: c->%b) ", a, b, c, d, sel, out);
            Fault_Indicator = 0; 
        end    

        a = 1;
        b = 0;
        c = 1;
        d = 0;
        sel = 11;

        #5;
        if(out != 0) begin
            $display("Test FAILED For (%b %b %b %b and sel=%b) (Expected Result: out->0) (But ALU Result is: s->%b)!!  ", a, b, c, d, sel, out);
            Fault_Indicator = 1;
        end
        else begin
            $display("Test Passed For (%b %b %b %b and sel=%b) (Expected Result: out->0) (And ALU Result is: c->%b) ", a, b, c, d, sel, out);
            Fault_Indicator = 0; 
        end 
         
        a = 1;
        b = 0;
        c = 1;
        d = 0;
        sel = 01;

        #5;
        if(out != 0) begin
            $display("Test FAILED For (%b %b %b %b and sel=%b) (Expected Result: out->0) (But ALU Result is: s->%b)!!  ", a, b, c, d, sel, out);
            Fault_Indicator = 1;
        end
        else begin
            $display("Test Passed For (%b %b %b %b and sel=%b) (Expected Result: out->0) (And ALU Result is: c->%b) ", a, b, c, d, sel, out);
            Fault_Indicator = 0; 
        end   

        a = 1;
        b = 0;
        c = 1;
        d = 0;
        sel = 10;

        #5;
        if(out != 1) begin
            $display("Test FAILED For (%b %b %b %b and sel=%b) (Expected Result: out->1) (But ALU Result is: s->%b)!!  ", a, b, c, d, sel, out);
            Fault_Indicator = 1;
        end
        else begin
            $display("Test Passed For (%b %b %b %b and sel=%b) (Expected Result: out->1) (And ALU Result is: c->%b) ", a, b, c, d, sel, out);
            Fault_Indicator = 0; 
        end 

        a = 1;
        b = 0;
        c = 1;
        d = 0;
        sel = 00;

        #5;
        if(out != 1) begin
            $display("Test FAILED For (%b %b %b %b and sel=%b) (Expected Result: out->1) (But ALU Result is: s->%b)!!  ", a, b, c, d, sel, out);
            Fault_Indicator = 1;
        end
        else begin
            $display("Test Passed For (%b %b %b %b and sel=%b) (Expected Result: out->1) (And ALU Result is: c->%b) ", a, b, c, d, sel, out);
            Fault_Indicator = 0; 
        end  
    end

endmodule

Mux/Source_Codes/The_output.vcd
$date
	Fri Jun 16 10:47:28 2023
$end
$version
	Icarus Verilog
$end
$timescale
	1s
$end
$scope module alu_tb $end
$var reg 1 ! a $end
$upscope $end
$scope module alu_tb $end
$var reg 1 " b $end
$upscope $end
$scope module alu_tb $end
$var reg 1 # c $end
$upscope $end
$scope module alu_tb $end
$var reg 1 $ d $end
$upscope $end
$scope module alu_tb $end
$var reg 2 % sel [1:0] $end
$upscope $end
$scope module alu_tb $end
$var wire 1 & out $end
$upscope $end
$scope module alu_tb $end
$var reg 1 ' Fault_Indicator $end
$upscope $end
$enddefinitions $end
#0
$dumpvars
0'
0&
b0 %
1$
0#
1"
0!
$end
#5
1&
b1 %
#10
0&
b10 %
#15
1&
b11 %
#20
0&
0$
1#
0"
1!
#25
b1 %
#30
1&
b10 %
#35
b0 %
